elektronn2/__init__.py
elektronn2/_version.py
elektronn2/config.py
elektronn2/data/__init__.py
elektronn2/data/cnndata.py
elektronn2/data/image.py
elektronn2/data/knossos_array.py
elektronn2/data/non_geometric_augmentation.py
elektronn2/data/skeleton.py
elektronn2/data/tracing_utils.py
elektronn2/data/traindata.py
elektronn2/data/transformations.py
elektronn2/malis/__init__.py
elektronn2/malis/malis_utils.py
elektronn2/malis/malisop.py
elektronn2/neuromancer/__init__.py
elektronn2/neuromancer/computations.py
elektronn2/neuromancer/graphmanager.py
elektronn2/neuromancer/graphutils.py
elektronn2/neuromancer/loss.py
elektronn2/neuromancer/model.py
elektronn2/neuromancer/neural.py
elektronn2/neuromancer/node_basic.py
elektronn2/neuromancer/optimiser.py
elektronn2/neuromancer/variables.py
elektronn2/neuromancer/various.py
elektronn2/training/__init__.py
elektronn2/training/parallelisation.py
elektronn2/training/trainer.py
elektronn2/training/trainutils.py
elektronn2/utils/__init__.py
elektronn2/utils/cnncalculator.py
elektronn2/utils/gpu.py
elektronn2/utils/legacy.py
elektronn2/utils/locking.py
elektronn2/utils/plotting.py
elektronn2/utils/ptk_completions.py
elektronn2/utils/utils_basic.py
elektronn2/utils/d3viz/__init__.py
elektronn2/utils/d3viz/formatting.py
elektronn2/utils/d3viz/css/d3-context-menu.css
elektronn2/utils/d3viz/css/d3viz.css
elektronn2/utils/d3viz/html/template.html
elektronn2/utils/d3viz/js/d3-context-menu.js
elektronn2/utils/d3viz/js/d3.v3.min.js
elektronn2/utils/d3viz/js/d3viz.js
elektronn2/utils/d3viz/js/dagre-d3.min.js
elektronn2/utils/d3viz/js/graphlib-dot.min.js
elektronn2-0.6.0.data/scripts/elektronn2-profile
elektronn2-0.6.0.data/scripts/elektronn2-train
elektronn2-0.6.0.dist-info/METADATA
elektronn2-0.6.0.dist-info/RECORD
elektronn2-0.6.0.dist-info/WHEEL
elektronn2-0.6.0.dist-info/top_level.txt
