Metadata-Version: 2.1
Name: elektronn2
Version: 0.6.0
Summary: ELEKTRONN2 a is highly configurable toolkit for training 3d/2d CNNs and general Neural Networks
Home-page: http://www.elektronn.org/
Author: Marius Killinger
Author-email: Marius.Killinger@mailbox.org
License: GPL
Keywords: cnn theano neural network machine learning classification
Platform: UNKNOWN
Classifier: Development Status :: 3 - Alpha
Classifier: Intended Audience :: Science/Research
Classifier: Topic :: Scientific/Engineering :: Artificial Intelligence
Classifier: Topic :: Scientific/Engineering :: Information Analysis
Provides-Extra: knossos
Provides-Extra: ipython
Requires-Dist: numpy (>=1.8)
Requires-Dist: scipy (>=0.14)
Requires-Dist: matplotlib (>=1.4)
Requires-Dist: h5py (>=2.2)
Requires-Dist: theano (<0.10,>=0.8)
Requires-Dist: future (>=0.15)
Requires-Dist: tqdm (>=4.5)
Requires-Dist: colorlog (>=2.7)
Requires-Dist: prompt-toolkit (<2,>=1.0.3)
Requires-Dist: jedi (>=0.9.0)
Requires-Dist: pydotplus
Requires-Dist: seaborn
Requires-Dist: scikit-learn
Requires-Dist: psutil (>=5.0.1)
Requires-Dist: scikit-image (>=0.12.3)
Requires-Dist: numba (>=0.25)
Provides-Extra: ipython
Requires-Dist: ipython; extra == 'ipython'
Provides-Extra: knossos
Requires-Dist: knossos-utils; extra == 'knossos'
